easy_pytools/README.md
easy_pytools/__init__.py
easy_pytools/dto/README.md
easy_pytools/dto/__init__.py
easy_pytools/dto/_internal.py
easy_pytools/dto/decorators.py
easy_pytools/sql/README.md
easy_pytools/sql/_Base.py
easy_pytools/sql/_FieldConstraints.py
easy_pytools/sql/_Query.py
easy_pytools/sql/_Table.py
easy_pytools/sql/_Where.py
easy_pytools/sql/__init__.py
easy_pytools/sql/_exceptions.py
easy_pytools/sql/_internal.py
easy_pytools/sql/aggregate.py
easy_pytools/sql/parsing.py
easy_pytools/sql/queries/__init__.py
easy_pytools/structures/README.md
easy_pytools/structures/__init__.py
easy_pytools/structures/_internal.py
easy_pytools/structures/graphs.py
easy_pytools/structures/primitives.py
easy_pytools/structures/trees.py
easy_pytools/structures/cpp_lib/dist/libprimitives_lib.so
easy_pytools/structures/cpp_lib/dist/libtrees_lib.so
easy_pytools/structures/cpp_lib/dist/primitives.so
easy_pytools/structures/cpp_lib/dist/trees.so
easy_pytools/structures/pygraphs/_Graph.py
easy_pytools/structures/pygraphs/_OrientedGraph.py
easy_pytools/structures/pygraphs/__init__.py
easy_pytools/structures/pytrees/_BinaryTree.py
easy_pytools/structures/pytrees/_PrefixTree.py
easy_pytools/structures/pytrees/__init__.py
easy_pytools-1.0.4.dist-info/LICENSE
easy_pytools-1.0.4.dist-info/METADATA
easy_pytools-1.0.4.dist-info/WHEEL
easy_pytools-1.0.4.dist-info/top_level.txt
easy_pytools-1.0.4.dist-info/RECORD
