Metadata-Version: 2.1
Name: easy-pytools
Version: 1.0.4
Summary: Simple toolset with Python type hints made to deserve some needs on some Python projects.
Home-page: https://github.com/pushsla/easy-python-tools
Author: Svyatoslav Pushkarev
Author-email: push2001sla@gmail.com
License: GNU General Public License v3 or later (GPLv3 or later)
Classifier: Programming Language :: Python :: 3.10
Classifier: License :: OSI Approved :: GNU General Public License v3 (GPLv3)
Classifier: Operating System :: OS Independent
Requires-Python: >=3.10
License-File: LICENSE
